robust_crawl/__init__.py
robust_crawl/exceptions.py
robust_crawl/page_func.py
robust_crawl/page_pool.py
robust_crawl/playwright_backend.py
robust_crawl/proxy_creator.py
robust_crawl/proxy_manager.py
robust_crawl/request_pool.py
robust_crawl/singleton_meta.py
robust_crawl/token_bucket.py
robust_crawl-0.1.4.dist-info/LICENSE
robust_crawl-0.1.4.dist-info/METADATA
robust_crawl-0.1.4.dist-info/WHEEL
robust_crawl-0.1.4.dist-info/top_level.txt
robust_crawl-0.1.4.dist-info/RECORD
