Metadata-Version: 2.1
Name: robust_crawl
Version: 0.1.4
Summary: A library for robust crawler based on proxy pool and token bucket, support browser and requests
Author-email: Haoyu Wang <Haoyu_Wang_1103@outlook.com>
Classifier: Programming Language :: Python :: 3
Classifier: License :: OSI Approved :: MIT License
Classifier: Operating System :: OS Independent
Requires-Python: >=3.11
License-File: LICENSE
Requires-Dist: gevent
Requires-Dist: playwright
Requires-Dist: tenacity
Requires-Dist: brotli
Requires-Dist: numpy
Requires-Dist: requests
Requires-Dist: pyyaml
Requires-Dist: bs4
Requires-Dist: fake-useragent
Requires-Dist: openai
Requires-Dist: httpx
Requires-Dist: socksio
Requires-Dist: PySocks
